LICENSE
README.md
setup.py
src/tension/__init__.py
src/tension/base.py
src/tension/callbacks.py
src/tension/constrained.py
src/tension/esn.py
src/tension/models.py
src/tension/spiking.py
src/tension.egg-info/PKG-INFO
src/tension.egg-info/SOURCES.txt
src/tension.egg-info/dependency_links.txt
src/tension.egg-info/requires.txt
src/tension.egg-info/top_level.txt