Metadata-Version: 2.1
Name: tension
Version: 0.2
Summary: A Python package for training chaotic Echo State and Spiking RNNs
Home-page: https://github.com/zhenruiliao/tension
Author: Zhenrui Liao, Lu Bin Liu
Author-email: zhenrui.liao@columbia.edu
License: UNKNOWN
Project-URL: Bug Tracker, https://github.com/zhenruiliao/tension/issues
Platform: UNKNOWN
Classifier: Programming Language :: Python :: 3
Classifier: License :: OSI Approved :: MIT License
Classifier: Operating System :: OS Independent
Requires-Python: >=3.7
License-File: LICENSE
